kosong/__init__.py
kosong/__main__.py
kosong/_generate.py
kosong/chat_provider/__init__.py
kosong/chat_provider/chaos.py
kosong/chat_provider/echo.py
kosong/chat_provider/kimi.py
kosong/chat_provider/mock.py
kosong/chat_provider/openai_common.py
kosong/contrib/__init__.py
kosong/contrib/chat_provider/__init__.py
kosong/contrib/chat_provider/anthropic.py
kosong/contrib/chat_provider/common.py
kosong/contrib/chat_provider/google_genai.py
kosong/contrib/chat_provider/openai_legacy.py
kosong/contrib/chat_provider/openai_responses.py
kosong/contrib/context/__init__.py
kosong/contrib/context/linear.py
kosong/message.py
kosong/py.typed
kosong/tooling/__init__.py
kosong/tooling/empty.py
kosong/tooling/error.py
kosong/tooling/mcp.py
kosong/tooling/simple.py
kosong/utils/__init__.py
kosong/utils/aio.py
kosong/utils/jsonschema.py
kosong/utils/typing.py
kosong-0.38.0.dist-info/WHEEL
kosong-0.38.0.dist-info/METADATA
kosong-0.38.0.dist-info/RECORD
